MANIFEST.in
README.md
__about__.py
ponomarenko.py
setup.py
ponomarenko/Makefile
ponomarenko/algo.cpp
ponomarenko/algo.h
ponomarenko/curve_filter.cpp
ponomarenko/curve_filter.h
ponomarenko.egg-info/PKG-INFO
ponomarenko.egg-info/SOURCES.txt
ponomarenko.egg-info/dependency_links.txt
ponomarenko.egg-info/entry_points.txt
ponomarenko.egg-info/requires.txt
ponomarenko.egg-info/top_level.txt
ponomarenko/framework/CFramework.cpp
ponomarenko/framework/CFramework.h
ponomarenko/framework/CHistogram.cpp
ponomarenko/framework/CImage.cpp
ponomarenko/framework/CImage.h
ponomarenko/framework/CInspector.cpp
ponomarenko/framework/CInspector.h
ponomarenko/framework/framework.cpp
ponomarenko/framework/libparser.cpp
ponomarenko/framework/libparser.h
ponomarenko/framework/operations.cpp