Metadata-Version: 2.1
Name: ponomarenko
Version: 0.0.4.post1
Summary: Python bindings for M. Colom's IPOL Ponomarenko implementation
Home-page: https://github.com/cmla/ponomarenko.git
Author: Charles Hessel
Author-email: charles.hessel@ens-paris-saclay.fr
License: UNKNOWN
Platform: UNKNOWN
Requires-Python: >=3.5
